oblix/__init__.py
oblix/main.py
oblix/agents/__init__.py
oblix/agents/base.py
oblix/agents/connectivity/__init__.py
oblix/agents/connectivity/actions.py
oblix/agents/connectivity/agent.py
oblix/agents/connectivity/base.py
oblix/agents/connectivity/policies.py
oblix/agents/connectivity/darwin/__init__.py
oblix/agents/connectivity/darwin/monitor.py
oblix/agents/connectivity/linux/__init__.py
oblix/agents/connectivity/linux/monitor.py
oblix/agents/connectivity/windows/__init__.py
oblix/agents/connectivity/windows/monitor.py
oblix/agents/resource_monitor/__init__.py
oblix/agents/resource_monitor/actions.py
oblix/agents/resource_monitor/base.py
oblix/agents/resource_monitor/policies.py
oblix/agents/resource_monitor/darwin/__init__.py
oblix/agents/resource_monitor/darwin/macmon_wrapper.py
oblix/agents/resource_monitor/darwin/metal.py
oblix/agents/resource_monitor/darwin/monitor.py
oblix/agents/resource_monitor/darwin/simple_gpu_monitor.py
oblix/agents/resource_monitor/darwin/macmon/bin/macmon
oblix/agents/resource_monitor/linux/__init__.py
oblix/agents/resource_monitor/linux/monitor.py
oblix/agents/resource_monitor/windows/__init__.py
oblix/agents/resource_monitor/windows/monitor.py
oblix/api/__init__.py
oblix/api/routes.py
oblix/api/schemas.py
oblix/auth/__init__.py
oblix/auth/auth.py
oblix/cli/__init__.py
oblix/cli/main.py
oblix/cli/utils.py
oblix/cli/commands/__init__.py
oblix/cli/commands/agents.py
oblix/cli/commands/init.py
oblix/cli/commands/models.py
oblix/cli/commands/server.py
oblix/cli/commands/sessions.py
oblix/client/__init__.py
oblix/client/base_client.py
oblix/client/client.py
oblix/config/__init__.py
oblix/config/manager.py
oblix/connectors/__init__.py
oblix/connectors/documents/__init__.py
oblix/connectors/documents/manager.py
oblix/connectors/documents/processors.py
oblix/connectors/documents/storage.py
oblix/core/__init__.py
oblix/core/execution.py
oblix/core/websocket.py
oblix/models/__init__.py
oblix/models/base.py
oblix/models/claude.py
oblix-0.1.3.dist-info/licenses/LICENSE
oblix-0.1.3.dist-info/METADATA
oblix-0.1.3.dist-info/WHEEL
oblix-0.1.3.dist-info/entry_points.txt
oblix-0.1.3.dist-info/top_level.txt
oblix-0.1.3.dist-info/RECORD
