Metadata-Version: 2.4
Name: oblix
Version: 0.1.3
Summary: Oblix - Python SDK for AI model orchestration
Home-page: https://github.com/oblix-ai/oblix-python
Author: Oblix
Author-email: team@oblix.ai
License: Apache License 2.0
Keywords: ai sdk model orchestration
Classifier: Development Status :: 3 - Alpha
Classifier: Intended Audience :: Developers
Classifier: License :: OSI Approved :: Apache Software License
Classifier: Operating System :: OS Independent
Classifier: Programming Language :: Python :: 3
Classifier: Programming Language :: Python :: 3.8
Classifier: Programming Language :: Python :: 3.9
Classifier: Programming Language :: Python :: 3.10
Classifier: Programming Language :: Python :: 3.11
Classifier: Programming Language :: Python :: 3.12
Classifier: Programming Language :: Python :: 3.13
Requires-Python: >=3.8
License-File: LICENSE
Requires-Dist: aiohttp>=3.8.0
Requires-Dist: httpx>=0.24.0
Requires-Dist: openai>=1.0.0
Requires-Dist: anthropic>=0.9.0
Requires-Dist: tiktoken>=0.5.1
Requires-Dist: psutil>=5.8.0
Requires-Dist: pydantic>=1.8.0
Requires-Dist: python-dotenv>=0.19.0
Requires-Dist: pyyaml>=5.4.0
Requires-Dist: click>=8.0.0
Requires-Dist: colorama>=0.4.4
Requires-Dist: sqlalchemy
Requires-Dist: packaging>=23.0
Requires-Dist: fastapi>=0.68.0
Requires-Dist: uvicorn>=0.15.0
Requires-Dist: websockets>=10.0
Requires-Dist: python-multipart>=0.0.5
Requires-Dist: PyPDF2>=3.0.0
Requires-Dist: python-docx>=0.8.11
Requires-Dist: numpy>=1.20.0
Provides-Extra: dev
Requires-Dist: pytest>=7.0.0; extra == "dev"
Requires-Dist: pytest-asyncio>=0.20.0; extra == "dev"
Requires-Dist: pytest-cov>=4.0.0; extra == "dev"
Requires-Dist: flake8>=4.0.0; extra == "dev"
Requires-Dist: mypy>=1.0.0; extra == "dev"
Requires-Dist: black>=22.0.0; extra == "dev"
Requires-Dist: isort>=5.10.0; extra == "dev"
Provides-Extra: test
Requires-Dist: pytest>=7.0.0; extra == "test"
Requires-Dist: pytest-asyncio>=0.20.0; extra == "test"
Requires-Dist: pytest-cov>=4.0.0; extra == "test"
Requires-Dist: coverage; extra == "test"
Provides-Extra: windows
Requires-Dist: pywin32>=223; extra == "windows"
Requires-Dist: wmi>=1.5.1; extra == "windows"
Requires-Dist: pynvml>=11.5.0; extra == "windows"
Provides-Extra: linux
Requires-Dist: pynvml>=11.5.0; extra == "linux"
Provides-Extra: darwin
Dynamic: author
Dynamic: author-email
Dynamic: classifier
Dynamic: description
Dynamic: description-content-type
Dynamic: home-page
Dynamic: keywords
Dynamic: license
Dynamic: license-file
Dynamic: provides-extra
Dynamic: requires-dist
Dynamic: requires-python
Dynamic: summary
